MANIFEST.in
README.md
setup.py
PyJWT_mozilla.egg-info/PKG-INFO
PyJWT_mozilla.egg-info/SOURCES.txt
PyJWT_mozilla.egg-info/dependency_links.txt
PyJWT_mozilla.egg-info/requires.txt
PyJWT_mozilla.egg-info/top_level.txt
bin/jwt
jwt/__init__.py