Metadata-Version: 1.0
Name: PyJWT-mozilla
Version: 0.1.5
Summary: JSON Web Token implementation in Python
Home-page: http://github.com/rtilder/pyjwt
Author: Jeff Lindsay, Ryan Tilder
Author-email: rtilder@mozilla.com
License: MIT
Keywords: jwt json web token security signing
Platform: UNKNOWN
Classifier: Development Status :: 3 - Alpha
Classifier: Topic :: Utilities
Classifier: License :: OSI Approved :: MIT License
